docker_stack/__init__.py
docker_stack/cli.py
docker_stack/compose.py
docker_stack/docker_objects.py
docker_stack/envsubst.py
docker_stack/envsubst_merge.py
docker_stack/helpers.py
docker_stack/markers.py
docker_stack/merge_conf.py
docker_stack/registry.py
docker_stack/url_parser.py
docker_stack-0.3.1.dist-info/METADATA
docker_stack-0.3.1.dist-info/WHEEL
docker_stack-0.3.1.dist-info/entry_points.txt
docker_stack-0.3.1.dist-info/top_level.txt
docker_stack-0.3.1.dist-info/RECORD
