Metadata-Version: 2.4
Name: docker-stack
Version: 0.3.1
Summary: CLI for deploying and managing Docker stacks.
Home-page: https://github.com/mesudip/docker-stack
Author: Sudip Bhattarai
Author-email: sudip@bhattarai.me
Classifier: Programming Language :: Python :: 3
Classifier: License :: OSI Approved :: MIT License
Classifier: Operating System :: OS Independent
Requires-Python: >=3.6
Requires-Dist: PyYAML
Dynamic: author
Dynamic: author-email
Dynamic: classifier
Dynamic: description
Dynamic: description-content-type
Dynamic: home-page
Dynamic: requires-dist
Dynamic: requires-python
Dynamic: summary
